django_neomodel/__init__.py
django_neomodel/admin.py
django_neomodel/apps.py
django_neomodel/management/__init__.py
django_neomodel/management/commands/__init__.py
django_neomodel/management/commands/clear_neo4j.py
django_neomodel/management/commands/install_labels.py
scripts/docker-neo4j.sh
tests/.env
tests/Dockerfile
tests/__init__.py
tests/docker-compose.yml
tests/docker-entrypoint.sh
tests/manage.py
tests/settings.py
tests/urls.py
tests/someapp/__init__.py
tests/someapp/admin.py
tests/someapp/models.py
tests/someapp/views.py
tests/someapp/migrations/0001_initial.py
tests/someapp/migrations/__init__.py
tests/someapp/tests/__init__.py
tests/someapp/tests/test_atomicity.py
tests/someapp/tests/test_commands.py
tests/someapp/tests/test_model_form.py
tests/someapp/tests/test_sanity.py
tests/someapp/tests/test_signals.py
django_neomodel-0.2.0.dist-info/AUTHORS.txt
django_neomodel-0.2.0.dist-info/LICENSE
django_neomodel-0.2.0.dist-info/METADATA
django_neomodel-0.2.0.dist-info/WHEEL
django_neomodel-0.2.0.dist-info/top_level.txt
django_neomodel-0.2.0.dist-info/RECORD
