Metadata-Version: 2.1
Name: django_neomodel
Version: 0.2.0
Summary: Use Neo4j with Django!
Author-email: Robin Edwards <robin.ge@gmail.com>
Maintainer-email: Marius Conjeaud <marius.conjeaud@outlook.com>
License: MIT
Project-URL: repository, http://github.com/robinedwards/django-neomodel
Keywords: graph,neo4j,django,plugin,neomodel
Classifier: Development Status :: 4 - Beta
Classifier: Intended Audience :: Developers
Classifier: Operating System :: OS Independent
Classifier: License :: OSI Approved :: MIT License
Classifier: Programming Language :: Python
Classifier: Topic :: Software Development :: Libraries :: Python Modules
Classifier: Programming Language :: Python :: 3
Classifier: Topic :: Database
Requires-Python: >=3.8
License-File: LICENSE
License-File: AUTHORS.txt
Requires-Dist: neomodel~=5.3.0
Requires-Dist: django>=4.2.8
Provides-Extra: dev
Requires-Dist: pytest>=7.1; extra == "dev"
Requires-Dist: pytest-django>=4.5.2; extra == "dev"
Requires-Dist: pytest-cov>=4.0; extra == "dev"
